sphero_unsw/__init__.py
sphero_unsw/scanner.py
sphero_unsw/sphero_edu.py
sphero_unsw/toys_scanner.py
sphero_unsw/types.py
sphero_unsw/utils.py
sphero_unsw/commands/sensor.py
sphero_unsw/toy/bolt.py
sphero_unsw/toy/boltplus.py
sphero_unsw-0.1.8.dist-info/licenses/LICENSE
sphero_unsw-0.1.8.dist-info/METADATA
sphero_unsw-0.1.8.dist-info/WHEEL
sphero_unsw-0.1.8.dist-info/top_level.txt
sphero_unsw-0.1.8.dist-info/RECORD
