Metadata-Version: 2.4
Name: sphero_unsw
Version: 0.1.8
Summary: Extensions and patches for spherov2 to support Sphero BOLT+ (UNSW Canberra fork)
Author-email: Kathryn Kasmarik <kathryn.kasmarik@unsw.edu.au>, Reda Ghanem <reda.ghanem@unsw.edu.au>
License-Expression: MIT
Project-URL: Homepage, https://github.com/redaghanem/sphero_unsw
Project-URL: Source, https://github.com/redaghanem/sphero_unsw
Keywords: sphero,sphero bolt,robotics,unsw
Classifier: Development Status :: 3 - Alpha
Classifier: Framework :: Robot Framework :: Library
Classifier: Intended Audience :: Education
Classifier: Operating System :: OS Independent
Classifier: Programming Language :: Python :: 3.7
Classifier: Programming Language :: Python :: 3.8
Classifier: Programming Language :: Python :: 3.9
Classifier: Programming Language :: Python :: 3.10
Requires-Python: <3.11,>=3.7
License-File: LICENSE
Requires-Dist: bleak
Requires-Dist: spherov2
Dynamic: license-file
